{"songNumber": 23, "title": "Desayuno, Almuerzo, Cena", "audioUrl": "https://media.mykaraoke.video/a9feb868-d651-48bf-9614-85307ced81c5/b45f8cdb-ab9f-4411-b717-073cbb646946/original.wav", "lyrics": [{"id": 0, "words": [{"id": 0, "text": "Mañana,", "duration": 0.75, "timestamp": 4.261}, {"id": 1, "text": "mañana", "duration": 0.51, "timestamp": 5.022}, {"id": 2, "text": "desayuno,", "duration": 0.69, "timestamp": 5.542}, {"id": 3, "text": "desayuno", "duration": 0.88, "timestamp": 6.242}]}, {"id": 1, "words": [{"id": 0, "text": "Leche,", "duration": 0.69, "timestamp": 7.323}, {"id": 1, "text": "pan,", "duration": 0.65, "timestamp": 8.023}, {"id": 2, "text": "fruta,", "duration": 0.75, "timestamp": 8.683}, {"id": 3, "text": "huevo", "duration": 2.557, "timestamp": 9.443}]}, {"id": 2, "words": [{"id": 0, "text": "Tarde,", "duration": 0.67, "timestamp": 13.045}, {"id": 1, "text": "Tarde", "duration": 0.59, "timestamp": 13.725}, {"id": 2, "text": "almuerzo,", "duration": 0.63, "timestamp": 14.325}, {"id": 3, "text": "almuerzo", "duration": 0.66, "timestamp": 14.965}]}, {"id": 3, "words": [{"id": 0, "text": "Sopa,", "duration": 0.45, "timestamp": 15.866}, {"id": 1, "text": "arroz,", "duration": 0.83, "timestamp": 16.326}, {"id": 2, "text": "pollo,", "duration": 0.49, "timestamp": 17.166}, {"id": 3, "text": "ensalada", "duration": 1.176, "timestamp": 17.666}]}, {"id": 4, "words": [{"id": 0, "text": "Noche,", "duration": 0.787, "timestamp": 21.531}, {"id": 1, "text": "noche", "duration": 0.67, "timestamp": 22.328}, {"id": 2, "text": "cena,", "duration": 0.71, "timestamp": 23.008}, {"id": 3, "text": "cena", "duration": 0.5, "timestamp": 23.728}]}, {"id": 5, "words": [{"id": 0, "text": "Pasta,", "duration": 0.49, "timestamp": 24.469}, {"id": 1, "text": "pescado,", "duration": 0.71, "timestamp": 24.969}, {"id": 2, "text": "verdura,", "duration": 0.71, "timestamp": 25.689}, {"id": 3, "text": "avena", "duration": 2.351, "timestamp": 26.409}]}, {"id": 6, "words": [{"id": 0, "text": "¡Desayuno,", "duration": 0.712, "timestamp": 29.113}, {"id": 1, "text": "almuerzo,", "duration": 0.355, "timestamp": 29.835}, {"id": 2, "text": "cena!", "duration": 0.872, "timestamp": 30.2}]}, {"id": 7, "words": [{"id": 0, "text": "¡Rico,", "duration": 0.258, "timestamp": 31.564}, {"id": 1, "text": "sano,", "duration": 0.293, "timestamp": 31.832}, {"id": 2, "text": "qué", "duration": 0.273, "timestamp": 32.135}, {"id": 3, "text": "problema!", "duration": 1.353, "timestamp": 32.418}]}, {"id": 8, "words": [{"id": 0, "text": "¡Desayuno,", "duration": 0.511, "timestamp": 34.823}, {"id": 1, "text": "almuerzo,", "duration": 0.533, "timestamp": 35.344}, {"id": 2, "text": "cena!", "duration": 1.386, "timestamp": 35.887}]}, {"id": 9, "words": [{"id": 0, "text": "¡Rico,", "duration": 0.31, "timestamp": 37.313}, {"id": 1, "text": "sano,", "duration": 0.39, "timestamp": 37.633}, {"id": 2, "text": "qué", "duration": 0.27, "timestamp": 38.033}, {"id": 3, "text": "problema!", "duration": 1.221, "timestamp": 38.313}]}, {"id": 10, "words": [{"id": 0, "text": "¡Desayuno,", "duration": 0.6, "timestamp": 41.955}, {"id": 1, "text": "almuerzo,", "duration": 0.47, "timestamp": 42.555}, {"id": 2, "text": "cena!", "duration": 0.64, "timestamp": 43.035}]}, {"id": 11, "words": [{"id": 0, "text": "¡Rico,", "duration": 0.31, "timestamp": 44.475}, {"id": 1, "text": "sano,", "duration": 0.37, "timestamp": 44.796}, {"id": 2, "text": "qué", "duration": 0.27, "timestamp": 45.176}, {"id": 3, "text": "problema!", "duration": 1.06, "timestamp": 45.456}]}, {"id": 12, "words": [{"id": 0, "text": "¡Desayuno,", "duration": 0.58, "timestamp": 47.677}, {"id": 1, "text": "almuerzo,", "duration": 0.47, "timestamp": 48.257}, {"id": 2, "text": "cena!", "duration": 1.12, "timestamp": 48.737}]}, {"id": 13, "words": [{"id": 0, "text": "¡Rico,", "duration": 0.29, "timestamp": 50.197}, {"id": 1, "text": "sano,", "duration": 0.37, "timestamp": 50.498}, {"id": 2, "text": "qué", "duration": 0.29, "timestamp": 50.878}, {"id": 3, "text": "problema!", "duration": 1.06, "timestamp": 51.178}]}]}